scrapy_fieldstats/__init__.py
scrapy_fieldstats/fieldstats.py
scrapy_fieldstats-0.2.0.dist-info/DESCRIPTION.rst
scrapy_fieldstats-0.2.0.dist-info/METADATA
scrapy_fieldstats-0.2.0.dist-info/RECORD
scrapy_fieldstats-0.2.0.dist-info/WHEEL
scrapy_fieldstats-0.2.0.dist-info/metadata.json
scrapy_fieldstats-0.2.0.dist-info/top_level.txt
