Metadata-Version: 2.0
Name: scrapy-fieldstats
Version: 0.2.0
Summary: A Scrapy extension to generate a summary of fields coverage from your scraped data.
Home-page: https://github.com/stummjr/scrapy-fieldstats
Author: Valdir Stumm Junior
Author-email: stummjr@gmail.com
License: MIT license
Keywords: scrapy fields stats
Platform: UNKNOWN
Classifier: Development Status :: 2 - Pre-Alpha
Classifier: Intended Audience :: Developers
Classifier: License :: OSI Approved :: MIT License
Classifier: Natural Language :: English
Classifier: Programming Language :: Python :: 3.5
Classifier: Programming Language :: Python :: 3.6
Classifier: Programming Language :: Python :: 3.7
Classifier: Programming Language :: Python :: 3.8
